AUTHORS.rst
CONTRIBUTING.rst
HISTORY.rst
LICENSE
MANIFEST.in
README.md
setup.cfg
setup.py
docs/Makefile
docs/authors.rst
docs/conf.py
docs/contributing.rst
docs/history.rst
docs/index.rst
docs/installation.rst
docs/make.bat
docs/readme.rst
docs/usage.rst
pycdmsapi/__init__.py
pycdmsapi/cli.py
pycdmsapi/pycdmsapi.py
pycdmsapi.egg-info/PKG-INFO
pycdmsapi.egg-info/SOURCES.txt
pycdmsapi.egg-info/dependency_links.txt
pycdmsapi.egg-info/entry_points.txt
pycdmsapi.egg-info/not-zip-safe
pycdmsapi.egg-info/requires.txt
pycdmsapi.egg-info/top_level.txt
tests/__init__.py
tests/test_pycdmsapi.py