Metadata-Version: 1.2
Name: pycdmsapi
Version: 0.1.0
Summary: pycdmsapi a Python server implementation for a common Web API for Climate Data Management Systems (CDMS)
Home-page: https://github.com/isedwards/pycdmsapi
Author: Ian Edwards
Author-email: ian.edwards@myacorn.com
License: MIT license
Keywords: pycdmsapi
Platform: UNKNOWN
Classifier: Development Status :: 2 - Pre-Alpha
Classifier: Intended Audience :: Developers
Classifier: License :: OSI Approved :: MIT License
Classifier: Natural Language :: English
Classifier: Programming Language :: Python :: 3
Classifier: Programming Language :: Python :: 3.6
Classifier: Programming Language :: Python :: 3.7
Classifier: Programming Language :: Python :: 3.8
Requires-Python: >=3.6
